vprolog/__init__.py
vprolog/__main__.py
vprolog/inference.py
vprolog/interpreter.py
vprolog/methdispatch.py
vprolog/prolog.lark
vprolog/prolog_operator.py
vprolog/prolog_parser.py
vprolog/prolog_structures.py
vprolog/substitution.py
vprolog/data/builtin.pl
vprolog/data/default_input.pl
vprolog-0.1.0.dist-info/LICENSE
vprolog-0.1.0.dist-info/METADATA
vprolog-0.1.0.dist-info/WHEEL
vprolog-0.1.0.dist-info/entry_points.txt
vprolog-0.1.0.dist-info/top_level.txt
vprolog-0.1.0.dist-info/RECORD
