Metadata-Version: 2.1
Name: vprolog
Version: 0.1.0
Summary: Incomplete Prolog interpreter in Python
Home-page: https://github.com/Vekteur/vprolog
Author: Victor Dheur
Author-email: vic.dheur@gmail.com
License: MIT
Platform: UNKNOWN
Classifier: License :: OSI Approved :: MIT License
Classifier: Programming Language :: Python
Classifier: Programming Language :: Python :: 3
License-File: LICENSE
Requires-Dist: lark (>=1)
